{
 "creation": "2018-08-30 22:06:51.092169",
 "doctype": "DocType",
 "editable_grid": 1,
 "engine": "InnoDB",
 "field_order": [
  "expense_claim",
  "employee",
  "employee_name",
  "amount",
  "payable_account"
 ],
 "fields": [
  {
   "fieldname": "expense_claim",
   "fieldtype": "Link",
   "in_list_view": 1,
   "label": "Expense Claim",
   "options": "Expense Claim"
  },
  {
   "fieldname": "employee",
   "fieldtype": "Link",
   "in_list_view": 1,
   "label": "Employee",
   "options": "Employee",
   "reqd": 1
  },
  {
   "fieldname": "amount",
   "fieldtype": "Currency",
   "in_list_view": 1,
   "label": "Amount",
   "reqd": 1
  },
  {
   "fieldname": "payable_account",
   "fieldtype": "Link",
   "label": "Payable Account",
   "options": "Account"
  },
  {
   "fetch_from": "employee.employee_name",
   "fieldname": "employee_name",
   "fieldtype": "Data",
   "label": "Employee name",
   "read_only": 1
  }
 ],
 "istable": 1,
 "modified": "2021-11-16 11:32:51.462603",
 "modified_by": "Administrator",
 "module": "ERPNextSwiss",
 "name": "Payment Proposal Expense",
 "owner": "Administrator",
 "permissions": [],
 "quick_entry": 1,
 "sort_field": "modified",
 "sort_order": "DESC",
 "track_changes": 1
}