{
 "creation": "2018-01-21 19:22:33.636599",
 "doctype": "DocType",
 "editable_grid": 1,
 "engine": "InnoDB",
 "field_order": [
  "employee",
  "amended_from",
  "column_break_employee",
  "employee_name",
  "section_period",
  "year",
  "column_period",
  "start_date",
  "column_period_2",
  "end_date",
  "section_benefits",
  "certificate_type",
  "column_benefits_1",
  "free_transport",
  "column_benefits_2",
  "lunch_checks",
  "section_salary",
  "salary",
  "catering",
  "car",
  "section_1",
  "other_salary",
  "irregular",
  "capital",
  "column_2",
  "other_salary_description",
  "irregular_description",
  "capital_description",
  "section_2",
  "participation",
  "board",
  "section_3",
  "other",
  "column_3",
  "other_description",
  "section_4",
  "gross_salary",
  "deduction_ahv",
  "deduction_pension",
  "deduction_pension_additional",
  "net_salary",
  "source_tax_deduction",
  "effective_expenses_travel_check",
  "effective_expenses_travel",
  "section_5",
  "effective_other_expenses",
  "column_4",
  "effective_other_expenses_description",
  "section_6",
  "representation_expenses",
  "car_expenses",
  "section_7",
  "other_net_expenses",
  "column_5",
  "other_net_expenses_description",
  "section_8",
  "education",
  "section_9",
  "other_salary_sides",
  "column_6",
  "remarks"
 ],
 "fields": [
  {
   "fieldname": "employee",
   "fieldtype": "Link",
   "in_list_view": 1,
   "label": "Employee",
   "options": "Employee",
   "reqd": 1
  },
  {
   "fieldname": "amended_from",
   "fieldtype": "Link",
   "label": "Amended From",
   "no_copy": 1,
   "options": "Salary Certificate",
   "print_hide": 1,
   "read_only": 1
  },
  {
   "fieldname": "column_break_employee",
   "fieldtype": "Column Break"
  },
  {
   "fetch_from": "employee.employee_name",
   "fieldname": "employee_name",
   "fieldtype": "Data",
   "in_list_view": 1,
   "in_standard_filter": 1,
   "label": "Name",
   "read_only": 1
  },
  {
   "fieldname": "section_period",
   "fieldtype": "Section Break",
   "label": "Period"
  },
  {
   "fieldname": "year",
   "fieldtype": "Int",
   "label": "Year"
  },
  {
   "fieldname": "column_period",
   "fieldtype": "Column Break"
  },
  {
   "fieldname": "start_date",
   "fieldtype": "Date",
   "label": "Start date"
  },
  {
   "fieldname": "column_period_2",
   "fieldtype": "Column Break"
  },
  {
   "fieldname": "end_date",
   "fieldtype": "Date",
   "in_list_view": 1,
   "in_standard_filter": 1,
   "label": "End date"
  },
  {
   "fieldname": "section_benefits",
   "fieldtype": "Section Break",
   "label": "Benefits"
  },
  {
   "default": "Salary",
   "fieldname": "certificate_type",
   "fieldtype": "Select",
   "label": "Certificate type",
   "options": "Salary\nPension"
  },
  {
   "fieldname": "column_benefits_1",
   "fieldtype": "Column Break"
  },
  {
   "default": "0",
   "fieldname": "free_transport",
   "fieldtype": "Check",
   "label": "Free transport"
  },
  {
   "fieldname": "column_benefits_2",
   "fieldtype": "Column Break"
  },
  {
   "default": "0",
   "fieldname": "lunch_checks",
   "fieldtype": "Check",
   "label": "Lunch checks"
  },
  {
   "fieldname": "section_salary",
   "fieldtype": "Section Break",
   "label": "Section salary"
  },
  {
   "fieldname": "salary",
   "fieldtype": "Currency",
   "label": "1. Salary"
  },
  {
   "fieldname": "catering",
   "fieldtype": "Currency",
   "label": "2.1 Catering"
  },
  {
   "fieldname": "car",
   "fieldtype": "Currency",
   "label": "2.2 Car"
  },
  {
   "fieldname": "section_1",
   "fieldtype": "Section Break"
  },
  {
   "fieldname": "other_salary",
   "fieldtype": "Currency",
   "label": "2.3 Other salary"
  },
  {
   "fieldname": "irregular",
   "fieldtype": "Currency",
   "label": "3 Irregular"
  },
  {
   "fieldname": "capital",
   "fieldtype": "Currency",
   "label": "4 Capital"
  },
  {
   "fieldname": "column_2",
   "fieldtype": "Column Break"
  },
  {
   "fieldname": "other_salary_description",
   "fieldtype": "Data",
   "label": "2.3 Other salary description"
  },
  {
   "fieldname": "irregular_description",
   "fieldtype": "Data",
   "label": "3 Irregular description"
  },
  {
   "fieldname": "capital_description",
   "fieldtype": "Data",
   "label": "4 Capital description"
  },
  {
   "fieldname": "section_2",
   "fieldtype": "Section Break"
  },
  {
   "fieldname": "participation",
   "fieldtype": "Currency",
   "label": "5 Participation"
  },
  {
   "fieldname": "board",
   "fieldtype": "Currency",
   "label": "6 Board"
  },
  {
   "fieldname": "section_3",
   "fieldtype": "Section Break"
  },
  {
   "fieldname": "other",
   "fieldtype": "Currency",
   "label": "7 Other"
  },
  {
   "fieldname": "column_3",
   "fieldtype": "Column Break"
  },
  {
   "fieldname": "other_description",
   "fieldtype": "Data",
   "label": "7 Other description"
  },
  {
   "fieldname": "section_4",
   "fieldtype": "Section Break"
  },
  {
   "fieldname": "gross_salary",
   "fieldtype": "Currency",
   "label": "8 Gross salary",
   "read_only": 1
  },
  {
   "fieldname": "deduction_ahv",
   "fieldtype": "Currency",
   "label": "9 Deductions AHV/IV/EO/ALV/NBUV"
  },
  {
   "fieldname": "deduction_pension",
   "fieldtype": "Currency",
   "label": "10.1 Deduction pension"
  },
  {
   "fieldname": "deduction_pension_additional",
   "fieldtype": "Currency",
   "label": "10.2 Deduction pension additional"
  },
  {
   "bold": 1,
   "fieldname": "net_salary",
   "fieldtype": "Currency",
   "label": "11 Net salary",
   "read_only": 1
  },
  {
   "fieldname": "source_tax_deduction",
   "fieldtype": "Currency",
   "label": "12 Source tax deduction"
  },
  {
   "fieldname": "effective_expenses_travel",
   "fieldtype": "Currency",
   "label": "13.1.1 Effective expenses travel"
  },
  {
   "fieldname": "section_5",
   "fieldtype": "Section Break"
  },
  {
   "fieldname": "effective_other_expenses",
   "fieldtype": "Currency",
   "label": "13.1.2 Effective other expenses"
  },
  {
   "fieldname": "column_4",
   "fieldtype": "Column Break"
  },
  {
   "fieldname": "effective_other_expenses_description",
   "fieldtype": "Data",
   "label": "13.1.2 Effective other expenses description"
  },
  {
   "fieldname": "section_6",
   "fieldtype": "Section Break"
  },
  {
   "fieldname": "representation_expenses",
   "fieldtype": "Currency",
   "label": "13.2.1 Representation expenses"
  },
  {
   "fieldname": "car_expenses",
   "fieldtype": "Currency",
   "label": "13.2.2 Car expenses"
  },
  {
   "fieldname": "section_7",
   "fieldtype": "Section Break"
  },
  {
   "fieldname": "other_net_expenses",
   "fieldtype": "Currency",
   "label": "13.2.3 Other net expenses"
  },
  {
   "fieldname": "column_5",
   "fieldtype": "Column Break"
  },
  {
   "fieldname": "other_net_expenses_description",
   "fieldtype": "Data",
   "label": "13.2.3 Other net exenses description"
  },
  {
   "fieldname": "section_8",
   "fieldtype": "Section Break"
  },
  {
   "fieldname": "education",
   "fieldtype": "Currency",
   "label": "13.3 Education"
  },
  {
   "fieldname": "section_9",
   "fieldtype": "Section Break"
  },
  {
   "fieldname": "other_salary_sides",
   "fieldtype": "Data",
   "label": "14 Other salary sides"
  },
  {
   "fieldname": "column_6",
   "fieldtype": "Column Break"
  },
  {
   "fieldname": "remarks",
   "fieldtype": "Data",
   "label": "15 Remarks"
  },
  {
   "default": "0",
   "fieldname": "effective_expenses_travel_check",
   "fieldtype": "Check",
   "label": "13.1.1 Effective expenses travel"
  }
 ],
 "is_submittable": 1,
 "modified": "2023-01-18 18:07:10.534765",
 "modified_by": "Administrator",
 "module": "ERPNextSwiss",
 "name": "Salary Certificate",
 "owner": "Administrator",
 "permissions": [
  {
   "cancel": 1,
   "create": 1,
   "delete": 1,
   "email": 1,
   "export": 1,
   "print": 1,
   "read": 1,
   "report": 1,
   "role": "System Manager",
   "share": 1,
   "submit": 1,
   "write": 1
  },
  {
   "cancel": 1,
   "create": 1,
   "delete": 1,
   "email": 1,
   "export": 1,
   "print": 1,
   "read": 1,
   "report": 1,
   "role": "HR Manager",
   "share": 1,
   "submit": 1,
   "write": 1
  },
  {
   "create": 1,
   "email": 1,
   "export": 1,
   "print": 1,
   "read": 1,
   "report": 1,
   "role": "HR User",
   "share": 1,
   "write": 1
  }
 ],
 "sort_field": "modified",
 "sort_order": "DESC",
 "title_field": "employee_name",
 "track_changes": 1
}