{
 "creation": "2023-04-23 20:11:10.054377",
 "doctype": "DocType",
 "editable_grid": 1,
 "engine": "InnoDB",
 "field_order": [
  "dt",
  "field",
  "value"
 ],
 "fields": [
  {
   "fieldname": "dt",
   "fieldtype": "Link",
   "in_list_view": 1,
   "label": "DocType",
   "options": "DocType",
   "reqd": 1
  },
  {
   "fieldname": "field",
   "fieldtype": "Data",
   "in_list_view": 1,
   "label": "Field",
   "reqd": 1
  },
  {
   "fieldname": "value",
   "fieldtype": "Data",
   "in_list_view": 1,
   "label": "Value",
   "reqd": 1
  }
 ],
 "istable": 1,
 "modified": "2023-04-23 20:14:56.084470",
 "modified_by": "Administrator",
 "module": "ERPNextSwiss",
 "name": "ZUGFeRD Default Value",
 "owner": "Administrator",
 "permissions": [],
 "quick_entry": 1,
 "sort_field": "modified",
 "sort_order": "DESC",
 "track_changes": 1
}